api/endpoints.py
api/enums.py
api/models.py
auth/auth.py
core/client.py
core/config.py
core/http.py
swotzypy-0.1.0.dist-info/licenses/LICENSE
swotzypy-0.1.0.dist-info/METADATA
swotzypy-0.1.0.dist-info/WHEEL
swotzypy-0.1.0.dist-info/top_level.txt
swotzypy-0.1.0.dist-info/RECORD
