Metadata-Version: 2.4
Name: swotzypy
Version: 0.1.0
Summary: Swotzy API python wrapper
Author: MaKxex
Author-email: MaKxex <maksimos651@gmail.com>
License-Expression: MIT
Project-URL: Homepage, https://github.com/MaKxex/swotzyPy
Keywords: swotzy,api,wrapper,shipping,logistics
Classifier: Development Status :: 3 - Alpha
Classifier: Intended Audience :: Developers
Classifier: Programming Language :: Python :: 3
Classifier: Programming Language :: Python :: 3.8
Classifier: Programming Language :: Python :: 3.9
Classifier: Programming Language :: Python :: 3.10
Classifier: Programming Language :: Python :: 3.11
Classifier: Topic :: Software Development :: Libraries :: Python Modules
Requires-Python: >=3.8
License-File: LICENSE
Requires-Dist: httpx>=0.24.0
Requires-Dist: pydantic>=2.0.0
Requires-Dist: typing-extensions>=4.0.0
Provides-Extra: dev
Requires-Dist: black>=22.0.0; extra == "dev"
Requires-Dist: isort>=5.10.0; extra == "dev"
Requires-Dist: mypy>=0.990; extra == "dev"
Requires-Dist: flake8>=5.0.0; extra == "dev"
Provides-Extra: license-files
Requires-Dist: LICENSE; extra == "license-files"
Dynamic: author
Dynamic: license-file
Dynamic: requires-python
